donationalerts/__init__.py
donationalerts/asyncio_api.py
donationalerts/constants.py
donationalerts/donationalerts.py
donationalerts/utils.py
donationalerts/version.py
donationalertsBOT-0.0.1.dist-info/METADATA
donationalertsBOT-0.0.1.dist-info/WHEEL
donationalertsBOT-0.0.1.dist-info/top_level.txt
donationalertsBOT-0.0.1.dist-info/RECORD
