Metadata-Version: 2.1
Name: donationalertsBOT
Version: 0.0.1
Summary: DonationAlertsAPI 2.0.2 fix
Author: febriguns
Author-email: febriguns@bk.ru
Classifier: Programming Language :: Python :: 3
Classifier: License :: OSI Approved :: MIT License
Classifier: Operating System :: OS Independent
Requires-Python: >=3.6
